deepdiff/__init__.py
deepdiff/anyset.py
deepdiff/base.py
deepdiff/commands.py
deepdiff/deephash.py
deepdiff/delta.py
deepdiff/diff.py
deepdiff/distance.py
deepdiff/helper.py
deepdiff/lfucache.py
deepdiff/model.py
deepdiff/operator.py
deepdiff/path.py
deepdiff/search.py
deepdiff/serialization.py
deepdiff6-6.2.0.dist-info/AUTHORS.md
deepdiff6-6.2.0.dist-info/LICENSE
deepdiff6-6.2.0.dist-info/METADATA
deepdiff6-6.2.0.dist-info/WHEEL
deepdiff6-6.2.0.dist-info/entry_points.txt
deepdiff6-6.2.0.dist-info/top_level.txt
deepdiff6-6.2.0.dist-info/zip-safe
deepdiff6-6.2.0.dist-info/RECORD
