Metadata-Version: 2.1
Name: deepdiff6
Version: 6.2.0
Summary: Deep Difference and Search of any Python object/data. Recreate objects by adding adding deltas to each other.
Home-page: https://github.com/seperman/deepdiff
Download-URL: https://github.com/seperman/deepdiff/tarball/master
Author: Seperman
Author-email: sep@zepworks.com
License: MIT
Classifier: Intended Audience :: Developers
Classifier: Operating System :: OS Independent
Classifier: Topic :: Software Development
Classifier: Programming Language :: Python :: 3.7
Classifier: Programming Language :: Python :: 3.8
Classifier: Programming Language :: Python :: 3.9
Classifier: Programming Language :: Python :: 3.10
Classifier: Programming Language :: Python :: Implementation :: PyPy
Classifier: Development Status :: 5 - Production/Stable
Classifier: License :: OSI Approved :: MIT License
Requires-Python: >=3.7
License-File: LICENSE
License-File: AUTHORS.md
Requires-Dist: ordered-set (<4.2.0,>=4.0.2)
Provides-Extra: cli
Requires-Dist: click (==8.1.3) ; extra == 'cli'
Requires-Dist: pyyaml (==6.0) ; extra == 'cli'
Requires-Dist: toml (==0.10.2) ; extra == 'cli'
Requires-Dist: clevercsv (==0.7.4) ; extra == 'cli'
